{
  "worldSeed": "coinage-mvp-seed",
  "sampleCount": 500,
  "selectedCount": 10,
  "representatives": {
    "archetypeReps": [
      {
        "id": "planet-62",
        "archetype": "superterran"
      },
      {
        "id": "planet-95",
        "archetype": "icy"
      },
      {
        "id": "planet-111",
        "archetype": "exotic"
      },
      {
        "id": "planet-128",
        "archetype": "mineral"
      },
      {
        "id": "planet-206",
        "archetype": "lush"
      },
      {
        "id": "planet-210",
        "archetype": "fragmented"
      },
      {
        "id": "planet-296",
        "archetype": "oceanic"
      },
      {
        "id": "planet-315",
        "archetype": "arid"
      }
    ]
  },
  "camera": {
    "viewport": {
      "width": 1920,
      "height": 1080
    },
    "fieldRadius": 360,
    "viewHeight": 208.79999999999998,
    "viewWidth": 371.19999999999993,
    "zoom": 2.85,
    "cameraCenter": {
      "x": 5.954930959070927,
      "y": -5.560077746775345
    }
  },
  "pairMetrics": {
    "sameArchetype": {
      "pair": [
        "planet-62",
        "planet-484"
      ],
      "archetype": "superterran",
      "featureDistance": 0.8925053243586698,
      "galaxyImageMad96": 0.06704268223493101,
      "largeImageMad96": 0.08918136120188816
    },
    "diffArchetypeClosest": {
      "pair": [
        "planet-206",
        "planet-296"
      ],
      "archetypes": [
        "lush",
        "oceanic"
      ],
      "featureDistance": 0.3404751300126927,
      "galaxyImageMad96": 0.06880474990922295,
      "largeImageMad96": 0.05913458265250545
    },
    "diffArchetypeFarthest": {
      "pair": [
        "planet-339",
        "planet-484"
      ],
      "archetypes": [
        "fragmented",
        "superterran"
      ],
      "featureDistance": 1.1460338090815478,
      "galaxyImageMad96": 0.09676011029411764,
      "largeImageMad96": 0.09700421545933188
    }
  },
  "perceptualPairMatrix": [
    {
      "a": "planet-62",
      "aArch": "superterran",
      "b": "planet-95",
      "bArch": "icy",
      "galaxyMad96": 0.06672836669389978,
      "largeMad96": 0.0807346983932462
    },
    {
      "a": "planet-62",
      "aArch": "superterran",
      "b": "planet-111",
      "bArch": "exotic",
      "galaxyMad96": 0.21457879448075529,
      "largeMad96": 0.10461629675018155
    },
    {
      "a": "planet-62",
      "aArch": "superterran",
      "b": "planet-128",
      "bArch": "mineral",
      "galaxyMad96": 0.06695743690994917,
      "largeMad96": 0.03565112677015251
    },
    {
      "a": "planet-62",
      "aArch": "superterran",
      "b": "planet-206",
      "bArch": "lush",
      "galaxyMad96": 0.0888191040305011,
      "largeMad96": 0.10744995915032679
    },
    {
      "a": "planet-62",
      "aArch": "superterran",
      "b": "planet-210",
      "bArch": "fragmented",
      "galaxyMad96": 0.056706012844952795,
      "largeMad96": 0.07586408405954975
    },
    {
      "a": "planet-62",
      "aArch": "superterran",
      "b": "planet-296",
      "bArch": "oceanic",
      "galaxyMad96": 0.06489537944807552,
      "largeMad96": 0.08484888457697894
    },
    {
      "a": "planet-62",
      "aArch": "superterran",
      "b": "planet-315",
      "bArch": "arid",
      "galaxyMad96": 0.09942314020515614,
      "largeMad96": 0.08881967138707335
    },
    {
      "a": "planet-95",
      "aArch": "icy",
      "b": "planet-111",
      "bArch": "exotic",
      "galaxyMad96": 0.22918354552469136,
      "largeMad96": 0.047149175063543936
    },
    {
      "a": "planet-95",
      "aArch": "icy",
      "b": "planet-128",
      "bArch": "mineral",
      "galaxyMad96": 0.07661228553921569,
      "largeMad96": 0.0863261392519971
    },
    {
      "a": "planet-95",
      "aArch": "icy",
      "b": "planet-206",
      "bArch": "lush",
      "galaxyMad96": 0.06869766135620915,
      "largeMad96": 0.06257815336782861
    },
    {
      "a": "planet-95",
      "aArch": "icy",
      "b": "planet-210",
      "bArch": "fragmented",
      "galaxyMad96": 0.0624602850399419,
      "largeMad96": 0.05098932802287582
    },
    {
      "a": "planet-95",
      "aArch": "icy",
      "b": "planet-296",
      "bArch": "oceanic",
      "galaxyMad96": 0.05158590345860566,
      "largeMad96": 0.03952886710239651
    },
    {
      "a": "planet-95",
      "aArch": "icy",
      "b": "planet-315",
      "bArch": "arid",
      "galaxyMad96": 0.09874046840958604,
      "largeMad96": 0.0705271026234568
    },
    {
      "a": "planet-111",
      "aArch": "exotic",
      "b": "planet-128",
      "bArch": "mineral",
      "galaxyMad96": 0.18606714097676108,
      "largeMad96": 0.10879757284858388
    },
    {
      "a": "planet-111",
      "aArch": "exotic",
      "b": "planet-206",
      "bArch": "lush",
      "galaxyMad96": 0.2541746096586783,
      "largeMad96": 0.03419259486201888
    },
    {
      "a": "planet-111",
      "aArch": "exotic",
      "b": "planet-210",
      "bArch": "fragmented",
      "galaxyMad96": 0.20912408655591866,
      "largeMad96": 0.06533309504357299
    },
    {
      "a": "planet-111",
      "aArch": "exotic",
      "b": "planet-296",
      "bArch": "oceanic",
      "galaxyMad96": 0.22985713961510532,
      "largeMad96": 0.04759454997276688
    },
    {
      "a": "planet-111",
      "aArch": "exotic",
      "b": "planet-315",
      "bArch": "arid",
      "galaxyMad96": 0.23753928944262892,
      "largeMad96": 0.047370302287581705
    },
    {
      "a": "planet-128",
      "aArch": "mineral",
      "b": "planet-206",
      "bArch": "lush",
      "galaxyMad96": 0.12840725989469862,
      "largeMad96": 0.10936237631626725
    },
    {
      "a": "planet-128",
      "aArch": "mineral",
      "b": "planet-210",
      "bArch": "fragmented",
      "galaxyMad96": 0.05204461124727669,
      "largeMad96": 0.07874072372004357
    },
    {
      "a": "planet-128",
      "aArch": "mineral",
      "b": "planet-296",
      "bArch": "oceanic",
      "galaxyMad96": 0.07273738198983297,
      "largeMad96": 0.08891044843863471
    },
    {
      "a": "planet-128",
      "aArch": "mineral",
      "b": "planet-315",
      "bArch": "arid",
      "galaxyMad96": 0.1243510859204793,
      "largeMad96": 0.09009494712236746
    },
    {
      "a": "planet-206",
      "aArch": "lush",
      "b": "planet-210",
      "bArch": "fragmented",
      "galaxyMad96": 0.09003764410856936,
      "largeMad96": 0.08279150780682644
    },
    {
      "a": "planet-206",
      "aArch": "lush",
      "b": "planet-296",
      "bArch": "oceanic",
      "galaxyMad96": 0.06880474990922295,
      "largeMad96": 0.05913458265250545
    },
    {
      "a": "planet-206",
      "aArch": "lush",
      "b": "planet-315",
      "bArch": "arid",
      "galaxyMad96": 0.06614200367647059,
      "largeMad96": 0.047153004720406684
    },
    {
      "a": "planet-210",
      "aArch": "fragmented",
      "b": "planet-296",
      "bArch": "oceanic",
      "galaxyMad96": 0.04352092978395061,
      "largeMad96": 0.03812480142519971
    },
    {
      "a": "planet-210",
      "aArch": "fragmented",
      "b": "planet-315",
      "bArch": "arid",
      "galaxyMad96": 0.10567470043572985,
      "largeMad96": 0.08250924791212781
    },
    {
      "a": "planet-296",
      "aArch": "oceanic",
      "b": "planet-315",
      "bArch": "arid",
      "galaxyMad96": 0.09748448279774874,
      "largeMad96": 0.06852830541938998
    }
  ],
  "selectedPlanets": [
    {
      "id": "planet-62",
      "archetype": "superterran",
      "surfaceCategory": "lush",
      "terrainProfile": "continental",
      "radius": 3.734836623889447,
      "oceanLevel": 0.30382536578923464,
      "mountainLevel": 0.7883463084763846,
      "bandingStrength": 0.1,
      "thermalActivity": 0.1738389254291542,
      "craterStrength": 0.12721036836057903,
      "atmosphereIntensity": 0
    },
    {
      "id": "planet-95",
      "archetype": "icy",
      "surfaceCategory": "ice",
      "terrainProfile": "fragmented",
      "radius": 3.6007913820115327,
      "oceanLevel": 0.34149553948547695,
      "mountainLevel": 0.7018392383826897,
      "bandingStrength": 0.36,
      "thermalActivity": 0.13191771514806896,
      "craterStrength": 0.4347829067956191,
      "atmosphereIntensity": 0.7560756114869379
    },
    {
      "id": "planet-111",
      "archetype": "exotic",
      "surfaceCategory": "toxic",
      "terrainProfile": "extreme",
      "radius": 4.666584433483154,
      "oceanLevel": 0.1719109840631485,
      "mountainLevel": 0.7359090636700393,
      "bandingStrength": 0.42,
      "thermalActivity": 0.6313271910101176,
      "craterStrength": 0.284104612591397,
      "atmosphereIntensity": 0.1925594590842258
    },
    {
      "id": "planet-128",
      "archetype": "mineral",
      "surfaceCategory": "mineral",
      "terrainProfile": "rough",
      "radius": 3.359609609709218,
      "oceanLevel": 0.07473139489861204,
      "mountainLevel": 0.7610345142548903,
      "bandingStrength": 0.18000000000000002,
      "thermalActivity": 0.3131035427646711,
      "craterStrength": 0.7739586519919801,
      "atmosphereIntensity": 0
    },
    {
      "id": "planet-206",
      "archetype": "lush",
      "surfaceCategory": "lush",
      "terrainProfile": "continental",
      "radius": 3.7906675917413235,
      "oceanLevel": 0.31614322538701817,
      "mountainLevel": 0.7643054106552154,
      "bandingStrength": 0.16,
      "thermalActivity": 0.12891623196564614,
      "craterStrength": 0.07250059773507529,
      "atmosphereIntensity": 0.47597205271650106
    },
    {
      "id": "planet-210",
      "archetype": "fragmented",
      "surfaceCategory": "barren",
      "terrainProfile": "fragmented",
      "radius": 2.8403572093622533,
      "oceanLevel": 0.05,
      "mountainLevel": 0.7310399897995404,
      "bandingStrength": 0.26,
      "thermalActivity": 0.36551996939862147,
      "craterStrength": 0.7144596119146794,
      "atmosphereIntensity": 0.5266875714617036
    },
    {
      "id": "planet-296",
      "archetype": "oceanic",
      "surfaceCategory": "ocean",
      "terrainProfile": "smooth",
      "radius": 3.2896372186735086,
      "oceanLevel": 0.4954400990810246,
      "mountainLevel": 0.7452245381716639,
      "bandingStrength": 0.12,
      "thermalActivity": 0.08767361451499164,
      "craterStrength": 0.14692832187684254,
      "atmosphereIntensity": 0.3198645664396137
    },
    {
      "id": "planet-315",
      "archetype": "arid",
      "surfaceCategory": "desert",
      "terrainProfile": "rough",
      "radius": 2.5859005770442596,
      "oceanLevel": 0.05,
      "mountainLevel": 0.718178418545425,
      "bandingStrength": 0.19,
      "thermalActivity": 0.27773525563627477,
      "craterStrength": 0.7434079256860541,
      "atmosphereIntensity": 0.3944228134540189
    },
    {
      "id": "planet-484",
      "archetype": "superterran",
      "surfaceCategory": "lush",
      "terrainProfile": "continental",
      "radius": 3.540537364110678,
      "oceanLevel": 0.2866876152082346,
      "mountainLevel": 0.7812114781526849,
      "bandingStrength": 0.1,
      "thermalActivity": 0.1428344344580546,
      "craterStrength": 0.19381153618842367,
      "atmosphereIntensity": 0.6687263758749515
    },
    {
      "id": "planet-339",
      "archetype": "fragmented",
      "surfaceCategory": "desert",
      "terrainProfile": "fragmented",
      "radius": 3.2961374530356933,
      "oceanLevel": 0.05,
      "mountainLevel": 0.7414122836749069,
      "bandingStrength": 0.26,
      "thermalActivity": 0.3450368510247208,
      "craterStrength": 0.42902203301638364,
      "atmosphereIntensity": 0
    }
  ]
}
