{
  "worldSeed": "coinage-mvp-seed",
  "sampleCount": 500,
  "selectedCount": 11,
  "representatives": {
    "archetypeReps": [
      {
        "id": "planet-35",
        "archetype": "volcanic"
      },
      {
        "id": "planet-62",
        "archetype": "superterran"
      },
      {
        "id": "planet-95",
        "archetype": "icy"
      },
      {
        "id": "planet-111",
        "archetype": "exotic"
      },
      {
        "id": "planet-128",
        "archetype": "mineral"
      },
      {
        "id": "planet-206",
        "archetype": "lush"
      },
      {
        "id": "planet-210",
        "archetype": "fragmented"
      },
      {
        "id": "planet-296",
        "archetype": "oceanic"
      },
      {
        "id": "planet-315",
        "archetype": "arid"
      },
      {
        "id": "planet-329",
        "archetype": "clouded"
      }
    ]
  },
  "camera": {
    "viewport": {
      "width": 1920,
      "height": 1080
    },
    "fieldRadius": 360,
    "viewHeight": 208.79999999999998,
    "viewWidth": 371.19999999999993,
    "zoom": 2.55,
    "cameraCenter": {
      "x": 5.954930959070927,
      "y": -5.560077746775345
    }
  },
  "pairMetrics": {
    "sameArchetype": {
      "pair": [
        "planet-62",
        "planet-322"
      ],
      "archetype": "superterran",
      "featureDistance": 0.32524914298428914,
      "galaxyImageMad96": 0.14995120733478579,
      "largeImageMad96": 0.08880109045933188
    },
    "diffArchetypeClosest": {
      "pair": [
        "planet-206",
        "planet-296"
      ],
      "archetypes": [
        "lush",
        "oceanic"
      ],
      "featureDistance": 0.34209176596453045,
      "galaxyImageMad96": 0.08037712191358025,
      "largeImageMad96": 0.06605902777777778
    },
    "diffArchetypeFarthest": {
      "pair": [
        "planet-35",
        "planet-296"
      ],
      "archetypes": [
        "volcanic",
        "oceanic"
      ],
      "featureDistance": 1.5306755350177188,
      "galaxyImageMad96": 0.11278367828612926,
      "largeImageMad96": 0.052014399509803924
    }
  },
  "perceptualPairMatrix": [
    {
      "a": "planet-35",
      "aArch": "volcanic",
      "b": "planet-62",
      "bArch": "superterran",
      "galaxyMad96": 0.1045222573983297,
      "largeMad96": 0.08338950163398694
    },
    {
      "a": "planet-35",
      "aArch": "volcanic",
      "b": "planet-95",
      "bArch": "icy",
      "galaxyMad96": 0.1335399929647785,
      "largeMad96": 0.05496366081154684
    },
    {
      "a": "planet-35",
      "aArch": "volcanic",
      "b": "planet-111",
      "bArch": "exotic",
      "galaxyMad96": 0.13245393064633262,
      "largeMad96": 0.053325986065722586
    },
    {
      "a": "planet-35",
      "aArch": "volcanic",
      "b": "planet-128",
      "bArch": "mineral",
      "galaxyMad96": 0.09710336102033407,
      "largeMad96": 0.08992147785039942
    },
    {
      "a": "planet-35",
      "aArch": "volcanic",
      "b": "planet-206",
      "bArch": "lush",
      "galaxyMad96": 0.14807268972403775,
      "largeMad96": 0.075166802832244
    },
    {
      "a": "planet-35",
      "aArch": "volcanic",
      "b": "planet-210",
      "bArch": "fragmented",
      "galaxyMad96": 0.10417503517610749,
      "largeMad96": 0.05520819149419027
    },
    {
      "a": "planet-35",
      "aArch": "volcanic",
      "b": "planet-296",
      "bArch": "oceanic",
      "galaxyMad96": 0.11278367828612926,
      "largeMad96": 0.052014399509803924
    },
    {
      "a": "planet-35",
      "aArch": "volcanic",
      "b": "planet-315",
      "bArch": "arid",
      "galaxyMad96": 0.1382937318445897,
      "largeMad96": 0.06599477464596949
    },
    {
      "a": "planet-35",
      "aArch": "volcanic",
      "b": "planet-329",
      "bArch": "clouded",
      "galaxyMad96": 0.16917409903776323,
      "largeMad96": 0.053907952069716776
    },
    {
      "a": "planet-62",
      "aArch": "superterran",
      "b": "planet-95",
      "bArch": "icy",
      "galaxyMad96": 0.0796991308097313,
      "largeMad96": 0.0698312397875817
    },
    {
      "a": "planet-62",
      "aArch": "superterran",
      "b": "planet-111",
      "bArch": "exotic",
      "galaxyMad96": 0.1064268734114016,
      "largeMad96": 0.09077350558278867
    },
    {
      "a": "planet-62",
      "aArch": "superterran",
      "b": "planet-128",
      "bArch": "mineral",
      "galaxyMad96": 0.05200631467864924,
      "largeMad96": 0.05921670751633987
    },
    {
      "a": "planet-62",
      "aArch": "superterran",
      "b": "planet-206",
      "bArch": "lush",
      "galaxyMad96": 0.13520773760893245,
      "largeMad96": 0.09151291303558459
    },
    {
      "a": "planet-62",
      "aArch": "superterran",
      "b": "planet-210",
      "bArch": "fragmented",
      "galaxyMad96": 0.040915770243282495,
      "largeMad96": 0.06378009826615831
    },
    {
      "a": "planet-62",
      "aArch": "superterran",
      "b": "planet-296",
      "bArch": "oceanic",
      "galaxyMad96": 0.06632781295388526,
      "largeMad96": 0.06920785675381264
    },
    {
      "a": "planet-62",
      "aArch": "superterran",
      "b": "planet-315",
      "bArch": "arid",
      "galaxyMad96": 0.1298683449074074,
      "largeMad96": 0.074321867057008
    },
    {
      "a": "planet-62",
      "aArch": "superterran",
      "b": "planet-329",
      "bArch": "clouded",
      "galaxyMad96": 0.12128934617828613,
      "largeMad96": 0.10312670206971677
    },
    {
      "a": "planet-95",
      "aArch": "icy",
      "b": "planet-111",
      "bArch": "exotic",
      "galaxyMad96": 0.0610028878449528,
      "largeMad96": 0.050631751543209876
    },
    {
      "a": "planet-95",
      "aArch": "icy",
      "b": "planet-128",
      "bArch": "mineral",
      "galaxyMad96": 0.09288889456245461,
      "largeMad96": 0.09739143631989833
    },
    {
      "a": "planet-95",
      "aArch": "icy",
      "b": "planet-206",
      "bArch": "lush",
      "galaxyMad96": 0.07629314746732027,
      "largeMad96": 0.0652756501906318
    },
    {
      "a": "planet-95",
      "aArch": "icy",
      "b": "planet-210",
      "bArch": "fragmented",
      "galaxyMad96": 0.07603769517066086,
      "largeMad96": 0.058367091049382716
    },
    {
      "a": "planet-95",
      "aArch": "icy",
      "b": "planet-296",
      "bArch": "oceanic",
      "galaxyMad96": 0.05878197054284677,
      "largeMad96": 0.041367811592229485
    },
    {
      "a": "planet-95",
      "aArch": "icy",
      "b": "planet-315",
      "bArch": "arid",
      "galaxyMad96": 0.1030672714687727,
      "largeMad96": 0.07259242238562091
    },
    {
      "a": "planet-95",
      "aArch": "icy",
      "b": "planet-329",
      "bArch": "clouded",
      "galaxyMad96": 0.0817990593228032,
      "largeMad96": 0.0566827512254902
    },
    {
      "a": "planet-111",
      "aArch": "exotic",
      "b": "planet-128",
      "bArch": "mineral",
      "galaxyMad96": 0.12029831608569354,
      "largeMad96": 0.12432895901416122
    },
    {
      "a": "planet-111",
      "aArch": "exotic",
      "b": "planet-206",
      "bArch": "lush",
      "galaxyMad96": 0.05610617510893247,
      "largeMad96": 0.03552347154139433
    },
    {
      "a": "planet-111",
      "aArch": "exotic",
      "b": "planet-210",
      "bArch": "fragmented",
      "galaxyMad96": 0.08760453544843863,
      "largeMad96": 0.07863845769789397
    },
    {
      "a": "planet-111",
      "aArch": "exotic",
      "b": "planet-296",
      "bArch": "oceanic",
      "galaxyMad96": 0.06911679602396514,
      "largeMad96": 0.05361703998729121
    },
    {
      "a": "planet-111",
      "aArch": "exotic",
      "b": "planet-315",
      "bArch": "arid",
      "galaxyMad96": 0.07892894426289035,
      "largeMad96": 0.049087690631808276
    },
    {
      "a": "planet-111",
      "aArch": "exotic",
      "b": "planet-329",
      "bArch": "clouded",
      "galaxyMad96": 0.06867709468046478,
      "largeMad96": 0.04525363675562818
    },
    {
      "a": "planet-128",
      "aArch": "mineral",
      "b": "planet-206",
      "bArch": "lush",
      "galaxyMad96": 0.15035715096223676,
      "largeMad96": 0.12841066403413218
    },
    {
      "a": "planet-128",
      "aArch": "mineral",
      "b": "planet-210",
      "bArch": "fragmented",
      "galaxyMad96": 0.0481724026416122,
      "largeMad96": 0.07285723606572259
    },
    {
      "a": "planet-128",
      "aArch": "mineral",
      "b": "planet-296",
      "bArch": "oceanic",
      "galaxyMad96": 0.08279746505083514,
      "largeMad96": 0.09608665804284677
    },
    {
      "a": "planet-128",
      "aArch": "mineral",
      "b": "planet-315",
      "bArch": "arid",
      "galaxyMad96": 0.14110328159041394,
      "largeMad96": 0.10716018178104576
    },
    {
      "a": "planet-128",
      "aArch": "mineral",
      "b": "planet-329",
      "bArch": "clouded",
      "galaxyMad96": 0.13865201751997097,
      "largeMad96": 0.12759140114379083
    },
    {
      "a": "planet-206",
      "aArch": "lush",
      "b": "planet-210",
      "bArch": "fragmented",
      "galaxyMad96": 0.11460985725308642,
      "largeMad96": 0.09872132012527232
    },
    {
      "a": "planet-206",
      "aArch": "lush",
      "b": "planet-296",
      "bArch": "oceanic",
      "galaxyMad96": 0.08037712191358025,
      "largeMad96": 0.06605902777777778
    },
    {
      "a": "planet-206",
      "aArch": "lush",
      "b": "planet-315",
      "bArch": "arid",
      "galaxyMad96": 0.07147785039941902,
      "largeMad96": 0.050382540168845316
    },
    {
      "a": "planet-206",
      "aArch": "lush",
      "b": "planet-329",
      "bArch": "clouded",
      "galaxyMad96": 0.080269040486565,
      "largeMad96": 0.05982576479665941
    },
    {
      "a": "planet-210",
      "aArch": "fragmented",
      "b": "planet-296",
      "bArch": "oceanic",
      "galaxyMad96": 0.05723166870915033,
      "largeMad96": 0.04956072417392883
    },
    {
      "a": "planet-210",
      "aArch": "fragmented",
      "b": "planet-315",
      "bArch": "arid",
      "galaxyMad96": 0.1126992839960058,
      "largeMad96": 0.0872353281590414
    },
    {
      "a": "planet-210",
      "aArch": "fragmented",
      "b": "planet-329",
      "bArch": "clouded",
      "galaxyMad96": 0.10630148760893246,
      "largeMad96": 0.059948455655410314
    },
    {
      "a": "planet-296",
      "aArch": "oceanic",
      "b": "planet-315",
      "bArch": "arid",
      "galaxyMad96": 0.10455332017066087,
      "largeMad96": 0.07440867261256354
    },
    {
      "a": "planet-296",
      "aArch": "oceanic",
      "b": "planet-329",
      "bArch": "clouded",
      "galaxyMad96": 0.09302662037037036,
      "largeMad96": 0.050426084785766156
    },
    {
      "a": "planet-315",
      "aArch": "arid",
      "b": "planet-329",
      "bArch": "clouded",
      "galaxyMad96": 0.11208554602396514,
      "largeMad96": 0.08017528481299926
    }
  ],
  "selectedPlanets": [
    {
      "id": "planet-35",
      "archetype": "volcanic",
      "surfaceCategory": "volcanic",
      "terrainProfile": "extreme",
      "radius": 3.4022160450873917,
      "oceanLevel": 0.05,
      "mountainLevel": 0.7473486750811338,
      "bandingStrength": 0.12000000000000001,
      "thermalActivity": 1,
      "craterStrength": 1,
      "atmosphereIntensity": 0.4757317078087572
    },
    {
      "id": "planet-62",
      "archetype": "superterran",
      "surfaceCategory": "lush",
      "terrainProfile": "continental",
      "radius": 3.6656729827063086,
      "oceanLevel": 0.30382536578923464,
      "mountainLevel": 0.7883463084763846,
      "bandingStrength": 0.08,
      "thermalActivity": 0.18426926095490345,
      "craterStrength": 0.13738719782942535,
      "atmosphereIntensity": 0
    },
    {
      "id": "planet-95",
      "archetype": "icy",
      "surfaceCategory": "ice",
      "terrainProfile": "fragmented",
      "radius": 3.5341100601224302,
      "oceanLevel": 0.34149553948547695,
      "mountainLevel": 0.7018392383826897,
      "bandingStrength": 0.34,
      "thermalActivity": 0.1398327780569531,
      "craterStrength": 0.46956553933926864,
      "atmosphereIntensity": 0.7560756114869379
    },
    {
      "id": "planet-111",
      "archetype": "exotic",
      "surfaceCategory": "toxic",
      "terrainProfile": "extreme",
      "radius": 4.580166203233466,
      "oceanLevel": 0.1719109840631485,
      "mountainLevel": 0.7359090636700393,
      "bandingStrength": 0.32,
      "thermalActivity": 0.6692068224707247,
      "craterStrength": 0.3068329815987088,
      "atmosphereIntensity": 0.1925594590842258
    },
    {
      "id": "planet-128",
      "archetype": "mineral",
      "surfaceCategory": "mineral",
      "terrainProfile": "rough",
      "radius": 3.2973946169368253,
      "oceanLevel": 0.07473139489861204,
      "mountainLevel": 0.7610345142548903,
      "bandingStrength": 0.13999999999999999,
      "thermalActivity": 0.33188975533055143,
      "craterStrength": 0.8358753441513386,
      "atmosphereIntensity": 0
    },
    {
      "id": "planet-206",
      "archetype": "lush",
      "surfaceCategory": "lush",
      "terrainProfile": "continental",
      "radius": 3.720470043746114,
      "oceanLevel": 0.31614322538701817,
      "mountainLevel": 0.7643054106552154,
      "bandingStrength": 0.13999999999999999,
      "thermalActivity": 0.13665120588358493,
      "craterStrength": 0.07830064555388132,
      "atmosphereIntensity": 0.47597205271650106
    },
    {
      "id": "planet-210",
      "archetype": "fragmented",
      "surfaceCategory": "barren",
      "terrainProfile": "fragmented",
      "radius": 2.7877580017814707,
      "oceanLevel": 0.05,
      "mountainLevel": 0.7310399897995404,
      "bandingStrength": 0.13999999999999999,
      "thermalActivity": 0.3874511675625388,
      "craterStrength": 0.7716163808678539,
      "atmosphereIntensity": 0.5266875714617036
    },
    {
      "id": "planet-296",
      "archetype": "oceanic",
      "surfaceCategory": "ocean",
      "terrainProfile": "smooth",
      "radius": 3.2287180109202955,
      "oceanLevel": 0.4954400990810246,
      "mountainLevel": 0.7452245381716639,
      "bandingStrength": 0.1,
      "thermalActivity": 0.09293403138589115,
      "craterStrength": 0.15868258762698995,
      "atmosphereIntensity": 0.3198645664396137
    },
    {
      "id": "planet-315",
      "archetype": "arid",
      "surfaceCategory": "desert",
      "terrainProfile": "rough",
      "radius": 2.538013529321218,
      "oceanLevel": 0.05,
      "mountainLevel": 0.718178418545425,
      "bandingStrength": 0.13999999999999999,
      "thermalActivity": 0.2943993709744513,
      "craterStrength": 0.8028805597409384,
      "atmosphereIntensity": 0.3944228134540189
    },
    {
      "id": "planet-329",
      "archetype": "clouded",
      "surfaceCategory": "ice",
      "terrainProfile": "smooth",
      "radius": 3.1137717905727436,
      "oceanLevel": 0.34850000663027164,
      "mountainLevel": 0.7204797832187265,
      "bandingStrength": 0.44,
      "thermalActivity": 0.17663771063555034,
      "craterStrength": 0.30832004167916627,
      "atmosphereIntensity": 0.6218703222492244
    },
    {
      "id": "planet-322",
      "archetype": "superterran",
      "surfaceCategory": "lush",
      "terrainProfile": "continental",
      "radius": 3.8195585245328694,
      "oceanLevel": 0.2820344001427293,
      "mountainLevel": 0.7911624913882463,
      "bandingStrength": 0.08,
      "thermalActivity": 0.1932247226146236,
      "craterStrength": 0.09917081147316098,
      "atmosphereIntensity": 0.14250463552666826
    }
  ]
}
